xcsv/plot/__init__.py
xcsv/plot/__main__.py
xcsv_plot-0.4.2.dist-info/entry_points.txt
xcsv_plot-0.4.2.dist-info/LICENSE
xcsv_plot-0.4.2.dist-info/WHEEL
xcsv_plot-0.4.2.dist-info/METADATA
xcsv_plot-0.4.2.dist-info/RECORD
