Metadata-Version: 2.1
Name: xcsv-plot
Version: 0.4.2
Summary: Subpackage for plotting extended CSV (XCSV) files
Home-page: https://github.com/paul-breen/xcsv-plot
License: Apache-2.0
Author: Paul Breen
Author-email: pbree@bas.ac.uk
Requires-Python: >=3.8,<4.0
Classifier: License :: OSI Approved :: Apache Software License
Classifier: Programming Language :: Python :: 3
Classifier: Programming Language :: Python :: 3.8
Classifier: Programming Language :: Python :: 3.9
Classifier: Programming Language :: Python :: 3.10
Classifier: Programming Language :: Python :: 3.11
Requires-Dist: matplotlib (>=3.5.2,<4.0.0)
Requires-Dist: xcsv (>=0.4,<1.0)
Project-URL: Documentation, https://github.com/paul-breen/xcsv-plot/blob/main/README.md
Project-URL: Repository, https://github.com/paul-breen/xcsv-plot
